epigenetics_utilities/__init__.py
epigenetics_utilities/cluster_regions.py
epigenetics_utilities/enrichment.py
epigenetics_utilities/gene.py
epigenetics_utilities/main.py
epigenetics_utilities/odds_ratio_intersection.py
epigenetics_utilities/plotting.py
epigenetics_utilities/util.py
epigenetics_utilities-1.0.2.dist-info/METADATA
epigenetics_utilities-1.0.2.dist-info/WHEEL
epigenetics_utilities-1.0.2.dist-info/entry_points.txt
epigenetics_utilities-1.0.2.dist-info/top_level.txt
epigenetics_utilities-1.0.2.dist-info/RECORD
