Metadata-Version: 2.2
Name: epigenetics_utilities
Version: 1.0.2
Summary: Epigenetics Utilities from the Downing Lab
Author: Nandor Laszik
License: MIT
Project-URL: homepage, https://github.com/downinglab/epigenetics_utilities
Project-URL: repository, https://github.com/downinglab/epigenetics_utilities
Requires-Dist: pandas
Requires-Dist: numpy
Requires-Dist: tqdm
Requires-Dist: pybedtools
Requires-Dist: pyranges
Requires-Dist: joblib
Provides-Extra: test
Requires-Dist: pytest; extra == "test"
Requires-Dist: pytest-runner; extra == "test"
